depp/Agg_model.py
depp/Agg_model_recon.py
depp/Model_new.py
depp/Model_pl.py
depp/Model_pl.split.py
depp/Model_recon.py
depp/__init__.py
depp/assign_cluster_by_placement.py
depp/combine_similar_seq.py
depp/count_gapped_ratio.py
depp/data.py
depp/data.split.py
depp/data_recon.py
depp/default_config.py
depp/depp_distance.py
depp/depp_distance_recon.py
depp/distance_correction.py
depp/filter_by_entropy_gap.sh
depp/get_names_by_entropy_gap.py
depp/get_read_data_by_masking.py
depp/get_tree_dist.py
depp/grep_jplace.py
depp/grep_seq.py
depp/grep_seq_group.py
depp/select_placement.py
depp/select_species_by_distance.py
depp/set_bl_one.py
depp/submodule.py
depp/test_scripts.py
depp/utils.py
depp_test-0.4.0.data/scripts/agg_dist.py
depp_test-0.4.0.data/scripts/comb_json.py
depp_test-0.4.0.data/scripts/count_gapped_ratio.py
depp_test-0.4.0.data/scripts/depp-place-rRNA-one-type.sh
depp_test-0.4.0.data/scripts/depp-place-rRNA.sh
depp_test-0.4.0.data/scripts/depp_distance.py
depp_test-0.4.0.data/scripts/filter_by_entropy_gap.sh
depp_test-0.4.0.data/scripts/get_names_by_entropy_gap.py
depp_test-0.4.0.data/scripts/get_tree_dist.py
depp_test-0.4.0.data/scripts/grep_jplace.py
depp_test-0.4.0.data/scripts/grep_seq.py
depp_test-0.4.0.data/scripts/grep_seq_group.py
depp_test-0.4.0.data/scripts/merge_json.py
depp_test-0.4.0.data/scripts/run_upp.sh
depp_test-0.4.0.data/scripts/select_species_by_distance.py
depp_test-0.4.0.data/scripts/seq_sep.py
depp_test-0.4.0.data/scripts/set_bl_one.py
depp_test-0.4.0.data/scripts/train_cluster_depp.sh
depp_test-0.4.0.data/scripts/train_depp.py
depp_test-0.4.0.data/scripts/train_depp_recon.py
depp_test-0.4.0.data/scripts/wol_placement.sh
depp_test-0.4.0.dist-info/LICENSE
depp_test-0.4.0.dist-info/METADATA
depp_test-0.4.0.dist-info/WHEEL
depp_test-0.4.0.dist-info/top_level.txt
depp_test-0.4.0.dist-info/RECORD
